Workbook

Sheet apple
A1: url | B1: automatic_timestamp | C1: manual_timestamp | D1: label_correctness
A2: https://www.apple.com/newsroom/2023/05/meet-3-winners-of-the-wwdc23-swift-student-challenge/ | B2: 45076 | C2: 45076 | D2: =IF(TRIM(C2&"")="","",IFERROR(IF(INT(B2)=IF(ISNUMBER(C2),INT(C2),DATEVALUE(TRIM(C2))),"Correct","Incorrect"),"Incorrect")) -> Correct
A3: https://www.apple.com/newsroom/2022/03/lettering-artist-belinda-kou-on-the-power-of-creative-community-and-ipad-air/ | B3: 44650 | C3: 44650 | D3: =IF(TRIM(C3&"")="","",IFERROR(IF(INT(B3)=IF(ISNUMBER(C3),INT(C3),DATEVALUE(TRIM(C3))),"Correct","Incorrect"),"Incorrect")) -> Correct
A4: https://www.apple.com/newsroom/2018/03/students-succeed-at-their-own-speed-with-ipad-and-mac/ | B4: 43186 | C4: 43186 | D4: =IF(TRIM(C4&"")="","",IFERROR(IF(INT(B4)=IF(ISNUMBER(C4),INT(C4),DATEVALUE(TRIM(C4))),"Correct","Incorrect"),"Incorrect")) -> Correct
A5: https://www.apple.com/newsroom/2022/02/simmone-taitt-wants-to-eliminate-maternal-health-inequities/ | B5: 44616 | C5: 44616 | D5: =IF(TRIM(C5&"")="","",IFERROR(IF(INT(B5)=IF(ISNUMBER(C5),INT(C5),DATEVALUE(TRIM(C5))),"Correct","Incorrect"),"Incorrect")) -> Correct
A6: https://www.apple.com/newsroom/2024/06/hbcu-students-chart-their-career-paths-in-americas-music-city/ | B6: 45470 | C6: 45470 | D6: =IF(TRIM(C6&"")="","",IFERROR(IF(INT(B6)=IF(ISNUMBER(C6),INT(C6),DATEVALUE(TRIM(C6))),"Correct","Incorrect"),"Incorrect")) -> Correct
A7: https://www.apple.com/newsroom/2023/05/assistiveware-ushers-in-next-generation-of-aac-technology/ | B7: 45063 | C7: 45063 | D7: =IF(TRIM(C7&"")="","",IFERROR(IF(INT(B7)=IF(ISNUMBER(C7),INT(C7),DATEVALUE(TRIM(C7))),"Correct","Incorrect"),"Incorrect")) -> Correct
A8: https://www.apple.com/newsroom/2023/02/mcintosh-seed-preserves-land-and-legacy-with-black-landowners-in-the-us-south/ | B8: 44972 | C8: 44972 | D8: =IF(TRIM(C8&"")="","",IFERROR(IF(INT(B8)=IF(ISNUMBER(C8),INT(C8),DATEVALUE(TRIM(C8))),"Correct","Incorrect"),"Incorrect")) -> Correct
A9: https://www.apple.com/newsroom/2019/08/creativity-and-community-come-together-at-apples-teacher-coding-academies/ | B9: 43684 | C9: 43684 | D9: =IF(TRIM(C9&"")="","",IFERROR(IF(INT(B9)=IF(ISNUMBER(C9),INT(C9),DATEVALUE(TRIM(C9))),"Correct","Incorrect"),"Incorrect")) -> Correct
A10: https://www.apple.com/newsroom/2021/08/a-new-type-of-healing-supported-by-apple/ | B10: 44434 | C10: 44434 | D10: =IF(TRIM(C10&"")="","",IFERROR(IF(INT(B10)=IF(ISNUMBER(C10),INT(C10),DATEVALUE(TRIM(C10))),"Correct","Incorrect"),"Incorrect")) -> Correct
A11: https://www.apple.com/newsroom/2023/05/a-california-school-district-is-reimagining-education-with-apple-learning-coach/ | B11: 45054 | C11: 45054 | D11: =IF(TRIM(C11&"")="","",IFERROR(IF(INT(B11)=IF(ISNUMBER(C11),INT(C11),DATEVALUE(TRIM(C11))),"Correct","Incorrect"),"Incorrect")) -> Correct
A12: https://www.apple.com/newsroom/2022/10/meet-seven-hispanic-and-latin-app-creators-breaking-barriers-with-technology/ | B12: 44840 | C12: 44840 | D12: =IF(TRIM(C12&"")="","",IFERROR(IF(INT(B12)=IF(ISNUMBER(C12),INT(C12),DATEVALUE(TRIM(C12))),"Correct","Incorrect"),"Incorrect")) -> Correct
A13: https://www.apple.com/newsroom/2021/12/community-caregivers-spread-hope-in-ghana-with-support-from-apple/ | B13: 44531 | C13: 44531 | D13: =IF(TRIM(C13&"")="","",IFERROR(IF(INT(B13)=IF(ISNUMBER(C13),INT(C13),DATEVALUE(TRIM(C13))),"Correct","Incorrect"),"Incorrect")) -> Correct
... A101: https://www.apple.com/newsroom/2023/07/new-immersive-ar-experience-brings-student-creativity-to-life/ | B101: 45112 | C101: 45112 | D101: =IF(TRIM(C101&"")="","",IFERROR(IF(INT(B101)=IF(ISNUMBER(C101),INT(C101),DATEVALUE(TRIM(C101))),"Correct","Incorrect"),"Incorrect")) -> Correct
C102: Label accuracy (reviewed) | D102: =IFERROR(COUNTIF(D2:D101,"Correct")/(COUNTIF(D2:D101,"Correct")+COUNTIF(D2:D101,"Incorrect")),"") -> 1
C103: Reviewed / sampled | D103: =(COUNTIF(D2:D101,"Correct")+COUNTIF(D2:D101,"Incorrect"))&" / 100" -> 100 / 100

Sheet au
A1: url | B1: automatic_timestamp | C1: manual_timestamp | D1: label_correctness
A2: https://askubuntu.com/questions/1398402/how-to-unistall-tauon-music-player | B2: 45509 | C2: 45509 | D2: =IF(TRIM(C2&"")="","",IFERROR(IF(INT(B2)=IF(ISNUMBER(C2),INT(C2),DATEVALUE(TRIM(C2))),"Correct","Incorrect"),"Incorrect")) -> Correct
A3: https://askubuntu.com/questions/779872/cant-type-in-evince-search-field | B3: 45463 | C3: 45463 | D3: =IF(TRIM(C3&"")="","",IFERROR(IF(INT(B3)=IF(ISNUMBER(C3),INT(C3),DATEVALUE(TRIM(C3))),"Correct","Incorrect"),"Incorrect")) -> Correct
A4: https://askubuntu.com/questions/312782/how-to-install-ubuntu-on-separate-hard-drive-in-a-dual-boot | B4: 44504 | C4: 44504 | D4: =IF(TRIM(C4&"")="","",IFERROR(IF(INT(B4)=IF(ISNUMBER(C4),INT(C4),DATEVALUE(TRIM(C4))),"Correct","Incorrect"),"Incorrect")) -> Correct
A5: https://askubuntu.com/questions/702873/dependency-problem-when-installing-kernel-4-2-6-on-nuc-computer-running-trusty | B5: 42335 | C5: 42335 | D5: =IF(TRIM(C5&"")="","",IFERROR(IF(INT(B5)=IF(ISNUMBER(C5),INT(C5),DATEVALUE(TRIM(C5))),"Correct","Incorrect"),"Incorrect")) -> Correct
A6: https://askubuntu.com/questions/686214/how-do-i-get-a-steam-controller-working | B6: 45734 | C6: 45734 | D6: =IF(TRIM(C6&"")="","",IFERROR(IF(INT(B6)=IF(ISNUMBER(C6),INT(C6),DATEVALUE(TRIM(C6))),"Correct","Incorrect"),"Incorrect")) -> Correct
A7: https://askubuntu.com/questions/413434/why-is-the-size-of-update-manager-different-from-time-to-time | B7: 41671 | C7: 41671 | D7: =IF(TRIM(C7&"")="","",IFERROR(IF(INT(B7)=IF(ISNUMBER(C7),INT(C7),DATEVALUE(TRIM(C7))),"Correct","Incorrect"),"Incorrect")) -> Correct
A8: https://askubuntu.com/questions/1410509/getting-top-bar-black-screen-when-changing-refresh-rate-dual-boot-with-windows | B8: 44708 | C8: 44708 | D8: =IF(TRIM(C8&"")="","",IFERROR(IF(INT(B8)=IF(ISNUMBER(C8),INT(C8),DATEVALUE(TRIM(C8))),"Correct","Incorrect"),"Incorrect")) -> Correct
A9: https://askubuntu.com/questions/1351092/if-i-choose-something-else-for-installing-ubuntu-20-04-in-which-partition-sho | B9: 44387 | C9: 44387 | D9: =IF(TRIM(C9&"")="","",IFERROR(IF(INT(B9)=IF(ISNUMBER(C9),INT(C9),DATEVALUE(TRIM(C9))),"Correct","Incorrect"),"Incorrect")) -> Correct
A10: https://askubuntu.com/questions/358686/booting-off-a-usb-drive | B10: 41854 | C10: 41854 | D10: =IF(TRIM(C10&"")="","",IFERROR(IF(INT(B10)=IF(ISNUMBER(C10),INT(C10),DATEVALUE(TRIM(C10))),"Correct","Incorrect"),"Incorrect")) -> Correct
A11: https://askubuntu.com/questions/104834/set-up-a-vpn-route-samba-over-it | B11: 42838 | C11: 42838 | D11: =IF(TRIM(C11&"")="","",IFERROR(IF(INT(B11)=IF(ISNUMBER(C11),INT(C11),DATEVALUE(TRIM(C11))),"Correct","Incorrect"),"Incorrect")) -> Correct
A12: https://askubuntu.com/questions/917655/is-there-a-way-to-manually-check-which-extra-packages-are-going-to-be-removed | B12: 42877 | C12: 42877 | D12: =IF(TRIM(C12&"")="","",IFERROR(IF(INT(B12)=IF(ISNUMBER(C12),INT(C12),DATEVALUE(TRIM(C12))),"Correct","Incorrect"),"Incorrect")) -> Correct
A13: https://askubuntu.com/questions/129096/hang-when-loading-off-usb-at-command-sysenter-do-call0x12-0x28 | B13: 41076 | C13: 41076 | D13: =IF(TRIM(C13&"")="","",IFERROR(IF(INT(B13)=IF(ISNUMBER(C13),INT(C13),DATEVALUE(TRIM(C13))),"Correct","Incorrect"),"Incorrect")) -> Correct
... A101: https://askubuntu.com/questions/674426/installing-linux-4-3-on-existing-ubuntu-release | B101: 42263 | C101: 42263 | D101: =IF(TRIM(C101&"")="","",IFERROR(IF(INT(B101)=IF(ISNUMBER(C101),INT(C101),DATEVALUE(TRIM(C101))),"Correct","Incorrect"),"Incorrect")) -> Correct
C102: Label accuracy (reviewed) | D102: =IFERROR(COUNTIF(D2:D101,"Correct")/(COUNTIF(D2:D101,"Correct")+COUNTIF(D2:D101,"Incorrect")),"") -> 1
C103: Reviewed / sampled | D103: =(COUNTIF(D2:D101,"Correct")+COUNTIF(D2:D101,"Incorrect"))&" / 100" -> 100 / 100

Sheet cafnr
A1: url | B1: automatic_timestamp | C1: manual_timestamp | D1: label_correctness
A2: https://cafnr.missouri.edu/stories/yanu-prasetyo-received-outstanding-student-contribution-award-from-mu-council-on-international-initiatives/ | B2: 44172 | C2: 44172 | D2: =IF(TRIM(C2&"")="","",IFERROR(IF(INT(B2)=IF(ISNUMBER(C2),INT(C2),DATEVALUE(TRIM(C2))),"Correct","Incorrect"),"Incorrect")) -> Correct
A3: https://cafnr.missouri.edu/stories/dairy-products-evaluation-team-sees-success-at-national-competition/ | B3: 45411 | C3: 45411 | D3: =IF(TRIM(C3&"")="","",IFERROR(IF(INT(B3)=IF(ISNUMBER(C3),INT(C3),DATEVALUE(TRIM(C3))),"Correct","Incorrect"),"Incorrect")) -> Correct
A4: https://cafnr.missouri.edu/stories/new-director-announced-for-raff/ | B4: 45460 | C4: 45460 | D4: =IF(TRIM(C4&"")="","",IFERROR(IF(INT(B4)=IF(ISNUMBER(C4),INT(C4),DATEVALUE(TRIM(C4))),"Correct","Incorrect"),"Incorrect")) -> Correct
A5: https://cafnr.missouri.edu/stories/environmental-sciences-students-get-hands-on-experience-creating-the-campus-weather-forecast/ | B5: 45610 | C5: 45610 | D5: =IF(TRIM(C5&"")="","",IFERROR(IF(INT(B5)=IF(ISNUMBER(C5),INT(C5),DATEVALUE(TRIM(C5))),"Correct","Incorrect"),"Incorrect")) -> Correct
A6: https://cafnr.missouri.edu/stories/bob-sharp-receives-um-systems-jefferson-award/ | B6: 45048 | C6: 45048 | D6: =IF(TRIM(C6&"")="","",IFERROR(IF(INT(B6)=IF(ISNUMBER(C6),INT(C6),DATEVALUE(TRIM(C6))),"Correct","Incorrect"),"Incorrect")) -> Correct
A7: https://cafnr.missouri.edu/stories/an-outstanding-recognition-2/ | B7: 44004 | C7: 44004 | D7: =IF(TRIM(C7&"")="","",IFERROR(IF(INT(B7)=IF(ISNUMBER(C7),INT(C7),DATEVALUE(TRIM(C7))),"Correct","Incorrect"),"Incorrect")) -> Correct
A8: https://cafnr.missouri.edu/stories/qa-with-jerry-richards/ | B8: 44852 | C8: 44852 | D8: =IF(TRIM(C8&"")="","",IFERROR(IF(INT(B8)=IF(ISNUMBER(C8),INT(C8),DATEVALUE(TRIM(C8))),"Correct","Incorrect"),"Incorrect")) -> Correct
A9: https://cafnr.missouri.edu/stories/a-growth-mindset/ | B9: 44883 | C9: 44883 | D9: =IF(TRIM(C9&"")="","",IFERROR(IF(INT(B9)=IF(ISNUMBER(C9),INT(C9),DATEVALUE(TRIM(C9))),"Correct","Incorrect"),"Incorrect")) -> Correct
A10: https://cafnr.missouri.edu/stories/cafnr-fish-ecologists-research-indicates-need-to-conserve-iconic-migratory-snook-in-mexico/ | B10: 45261 | C10: 45261 | D10: =IF(TRIM(C10&"")="","",IFERROR(IF(INT(B10)=IF(ISNUMBER(C10),INT(C10),DATEVALUE(TRIM(C10))),"Correct","Incorrect"),"Incorrect")) -> Correct
A11: https://cafnr.missouri.edu/stories/anthony-lupo-recognized-by-national-weather-association/ | B11: 44797 | C11: 44797 | D11: =IF(TRIM(C11&"")="","",IFERROR(IF(INT(B11)=IF(ISNUMBER(C11),INT(C11),DATEVALUE(TRIM(C11))),"Correct","Incorrect"),"Incorrect")) -> Correct
A12: https://cafnr.missouri.edu/stories/computers-come-to-cafnr/ | B12: 42048 | C12: 42048 | D12: =IF(TRIM(C12&"")="","",IFERROR(IF(INT(B12)=IF(ISNUMBER(C12),INT(C12),DATEVALUE(TRIM(C12))),"Correct","Incorrect"),"Incorrect")) -> Correct
A13: https://cafnr.missouri.edu/stories/leading-dass-harvey-s-james-jr-named-to-head-division-of-applied-social-sciences/ | B13: 45324 | C13: 45324 | D13: =IF(TRIM(C13&"")="","",IFERROR(IF(INT(B13)=IF(ISNUMBER(C13),INT(C13),DATEVALUE(TRIM(C13))),"Correct","Incorrect"),"Incorrect")) -> Correct
... A101: https://cafnr.missouri.edu/stories/cafnr-celebrates-womens-history-month-qa-with-melissa-joy-dobbins/ | B101: 45005 | C101: 45005 | D101: =IF(TRIM(C101&"")="","",IFERROR(IF(INT(B101)=IF(ISNUMBER(C101),INT(C101),DATEVALUE(TRIM(C101))),"Correct","Incorrect"),"Incorrect")) -> Correct
C102: Label accuracy (reviewed) | D102: =IFERROR(COUNTIF(D2:D101,"Correct")/(COUNTIF(D2:D101,"Correct")+COUNTIF(D2:D101,"Incorrect")),"") -> 1
C103: Reviewed / sampled | D103: =(COUNTIF(D2:D101,"Correct")+COUNTIF(D2:D101,"Incorrect"))&" / 100" -> 100 / 100

Sheet coas
A1: url | B1: automatic_timestamp | C1: manual_timestamp | D1: label_correctness
A2: https://coas.missouri.edu/news/undergrad-talk | B2: 44032 | C2: 44032 | D2: =IF(TRIM(C2&"")="","",IFERROR(IF(INT(B2)=IF(ISNUMBER(C2),INT(C2),DATEVALUE(TRIM(C2))),"Correct","Incorrect"),"Incorrect")) -> Correct
A3: https://coas.missouri.edu/news/professor-oded-gurantz-publishes-oregon-promise-program-research-jpam | B3: 43935 | C3: 43935 | D3: =IF(TRIM(C3&"")="","",IFERROR(IF(INT(B3)=IF(ISNUMBER(C3),INT(C3),DATEVALUE(TRIM(C3))),"Correct","Incorrect"),"Incorrect")) -> Correct
A4: https://coas.missouri.edu/news/mizzou-scientists-develop-method-could-lower-medicine-costs-and-contribute-cleaner-energy-and | B4: 45719 | C4: 45719 | D4: =IF(TRIM(C4&"")="","",IFERROR(IF(INT(B4)=IF(ISNUMBER(C4),INT(C4),DATEVALUE(TRIM(C4))),"Correct","Incorrect"),"Incorrect")) -> Correct
A5: https://coas.missouri.edu/news/katina-bitsicas-breaks-boundaries-digital-storytelling | B5: 45219 | C5: 45219 | D5: =IF(TRIM(C5&"")="","",IFERROR(IF(INT(B5)=IF(ISNUMBER(C5),INT(C5),DATEVALUE(TRIM(C5))),"Correct","Incorrect"),"Incorrect")) -> Correct
A6: https://coas.missouri.edu/news/chancellors-arts-showcase-program-2024 | B6: 45348 | C6: 45348 | D6: =IF(TRIM(C6&"")="","",IFERROR(IF(INT(B6)=IF(ISNUMBER(C6),INT(C6),DATEVALUE(TRIM(C6))),"Correct","Incorrect"),"Incorrect")) -> Correct
A7: https://coas.missouri.edu/news/emma-lipton-pens-cultures-witnessing-law-and-york-plays | B7: 44764 | C7: 44764 | D7: =IF(TRIM(C7&"")="","",IFERROR(IF(INT(B7)=IF(ISNUMBER(C7),INT(C7),DATEVALUE(TRIM(C7))),"Correct","Incorrect"),"Incorrect")) -> Correct
A8: https://coas.missouri.edu/news/afro-cuban-conference-connects-continents-and-cultures | B8: 45397 | C8: 45397 | D8: =IF(TRIM(C8&"")="","",IFERROR(IF(INT(B8)=IF(ISNUMBER(C8),INT(C8),DATEVALUE(TRIM(C8))),"Correct","Incorrect"),"Incorrect")) -> Correct
A9: https://coas.missouri.edu/news/preserving-more-just-music | B9: 45042 | C9: 45042 | D9: =IF(TRIM(C9&"")="","",IFERROR(IF(INT(B9)=IF(ISNUMBER(C9),INT(C9),DATEVALUE(TRIM(C9))),"Correct","Incorrect"),"Incorrect")) -> Correct
A10: https://coas.missouri.edu/news/photo-gallery-attic-finds | B10: 44851 | C10: 44851 | D10: =IF(TRIM(C10&"")="","",IFERROR(IF(INT(B10)=IF(ISNUMBER(C10),INT(C10),DATEVALUE(TRIM(C10))),"Correct","Incorrect"),"Incorrect")) -> Correct
A11: https://coas.missouri.edu/news/making-right-move | B11: 44851 | C11: 44851 | D11: =IF(TRIM(C11&"")="","",IFERROR(IF(INT(B11)=IF(ISNUMBER(C11),INT(C11),DATEVALUE(TRIM(C11))),"Correct","Incorrect"),"Incorrect")) -> Correct
A12: https://coas.missouri.edu/news/behind-velvet-curtain | B12: 44681 | C12: 44681 | D12: =IF(TRIM(C12&"")="","",IFERROR(IF(INT(B12)=IF(ISNUMBER(C12),INT(C12),DATEVALUE(TRIM(C12))),"Correct","Incorrect"),"Incorrect")) -> Correct
A13: https://coas.missouri.edu/news/researchers-create-solution-removes-more-98-nanoplastics-water | B13: 45518 | C13: 45518 | D13: =IF(TRIM(C13&"")="","",IFERROR(IF(INT(B13)=IF(ISNUMBER(C13),INT(C13),DATEVALUE(TRIM(C13))),"Correct","Incorrect"),"Incorrect")) -> Correct
... A101: https://coas.missouri.edu/news/professor-mueser-speaks-uncertainty-economy | B101: 44447 | C101: 44447 | D101: =IF(TRIM(C101&"")="","",IFERROR(IF(INT(B101)=IF(ISNUMBER(C101),INT(C101),DATEVALUE(TRIM(C101))),"Correct","Incorrect"),"Incorrect")) -> Correct
C102: Label accuracy (reviewed) | D102: =IFERROR(COUNTIF(D2:D101,"Correct")/(COUNTIF(D2:D101,"Correct")+COUNTIF(D2:D101,"Incorrect")),"") -> 1
C103: Reviewed / sampled | D103: =(COUNTIF(D2:D101,"Correct")+COUNTIF(D2:D101,"Incorrect"))&" / 100" -> 100 / 100

Sheet google
A1: url | B1: automatic_timestamp | C1: manual_timestamp | D1: label_correctness
A2: https://support.google.com/chrome/thread/365887732/shrot-viewed-problem?hl=en | B2: 45886 | C2: 45886 | D2: =IF(TRIM(C2&"")="","",IFERROR(IF(INT(B2)=IF(ISNUMBER(C2),INT(C2),DATEVALUE(TRIM(C2))),"Correct","Incorrect"),"Incorrect")) -> Correct
A3: https://support.google.com/chrome/thread/348924737/unsecure-site?hl=en | B3: 45814 | C3: 45814 | D3: =IF(TRIM(C3&"")="","",IFERROR(IF(INT(B3)=IF(ISNUMBER(C3),INT(C3),DATEVALUE(TRIM(C3))),"Correct","Incorrect"),"Incorrect")) -> Correct
A4: https://support.google.com/chrome/thread/349652463/aap-not-found-on-website-erroe?hl=en | B4: 45817 | C4: 45817 | D4: =IF(TRIM(C4&"")="","",IFERROR(IF(INT(B4)=IF(ISNUMBER(C4),INT(C4),DATEVALUE(TRIM(C4))),"Correct","Incorrect"),"Incorrect")) -> Correct
A5: https://support.google.com/chrome/thread/349913300/android-gray-website-loading-bar-visible-during-of-fullscreen-video?hl=en | B5: 45818 | C5: 45818 | D5: =IF(TRIM(C5&"")="","",IFERROR(IF(INT(B5)=IF(ISNUMBER(C5),INT(C5),DATEVALUE(TRIM(C5))),"Correct","Incorrect"),"Incorrect")) -> Correct
A6: https://support.google.com/chrome/thread/362982390/clicking-on-login-does-not-open-the-next-step?hl=en | B6: 45874 | C6: 45874 | D6: =IF(TRIM(C6&"")="","",IFERROR(IF(INT(B6)=IF(ISNUMBER(C6),INT(C6),DATEVALUE(TRIM(C6))),"Correct","Incorrect"),"Incorrect")) -> Correct
A7: https://support.google.com/chrome/thread/351198129/google-password-manager-doesn%E2%80%99t-give-the-option-to-manually-add-passwords?hl=en | B7: 45824 | C7: 45824 | D7: =IF(TRIM(C7&"")="","",IFERROR(IF(INT(B7)=IF(ISNUMBER(C7),INT(C7),DATEVALUE(TRIM(C7))),"Correct","Incorrect"),"Incorrect")) -> Correct
A8: https://support.google.com/chrome/thread/354872704/can-t-move-address-bar-to-the-bottom?hl=en | B8: 45841 | C8: 45841 | D8: =IF(TRIM(C8&"")="","",IFERROR(IF(INT(B8)=IF(ISNUMBER(C8),INT(C8),DATEVALUE(TRIM(C8))),"Correct","Incorrect"),"Incorrect")) -> Correct
A9: https://support.google.com/chrome/thread/353916208/unable-to-freely-select-and-copy-full-text-using-google-lens-as-before?hl=en | B9: 45837 | C9: 45837 | D9: =IF(TRIM(C9&"")="","",IFERROR(IF(INT(B9)=IF(ISNUMBER(C9),INT(C9),DATEVALUE(TRIM(C9))),"Correct","Incorrect"),"Incorrect")) -> Correct
A10: https://support.google.com/chrome/thread/363522969/google-password-manager-pin-required-for-windows-hello-setup?hl=en | B10: 45876 | C10: 45876 | D10: =IF(TRIM(C10&"")="","",IFERROR(IF(INT(B10)=IF(ISNUMBER(C10),INT(C10),DATEVALUE(TRIM(C10))),"Correct","Incorrect"),"Incorrect")) -> Correct
A11: https://support.google.com/chrome/thread/357264326/can-chrome-extensions-steal-passwords-saved-to-the-google-password-manager?hl=en | B11: 45851 | C11: 45851 | D11: =IF(TRIM(C11&"")="","",IFERROR(IF(INT(B11)=IF(ISNUMBER(C11),INT(C11),DATEVALUE(TRIM(C11))),"Correct","Incorrect"),"Incorrect")) -> Correct
A12: https://support.google.com/chrome/thread/355525140/problem-helps?hl=en | B12: 45854 | C12: 45854 | D12: =IF(TRIM(C12&"")="","",IFERROR(IF(INT(B12)=IF(ISNUMBER(C12),INT(C12),DATEVALUE(TRIM(C12))),"Correct","Incorrect"),"Incorrect")) -> Correct
A13: https://support.google.com/chrome/thread/363046601/by-mistakenly-my-child-entered-the-birth-year-wrongly-how-to-change-my-child-birth-year?hl=en | B13: 45874 | C13: 45874 | D13: =IF(TRIM(C13&"")="","",IFERROR(IF(INT(B13)=IF(ISNUMBER(C13),INT(C13),DATEVALUE(TRIM(C13))),"Correct","Incorrect"),"Incorrect")) -> Correct
... A101: https://support.google.com/chrome/thread/349585674/wrong-ccountry?hl=en | B101: 45820 | C101: 45820 | D101: =IF(TRIM(C101&"")="","",IFERROR(IF(INT(B101)=IF(ISNUMBER(C101),INT(C101),DATEVALUE(TRIM(C101))),"Correct","Incorrect"),"Incorrect")) -> Correct
C102: Label accuracy (reviewed) | D102: =IFERROR(COUNTIF(D2:D101,"Correct")/(COUNTIF(D2:D101,"Correct")+COUNTIF(D2:D101,"Incorrect")),"") -> 1
C103: Reviewed / sampled | D103: =(COUNTIF(D2:D101,"Correct")+COUNTIF(D2:D101,"Incorrect"))&" / 100" -> 100 / 100

Sheet healthline
A1: url | B1: automatic_timestamp | C1: manual_timestamp | D1: label_correctness
A2: https://www.healthline.com/health/ulcerative-colitis-take-control/treatment | B2: 45812 | C2: 45812 | D2: =IF(TRIM(C2&"")="","",IFERROR(IF(INT(B2)=IF(ISNUMBER(C2),INT(C2),DATEVALUE(TRIM(C2))),"Correct","Incorrect"),"Incorrect")) -> Correct
A3: https://www.healthline.com/nutrition/weight-loss-plateau | B3: 45348 | C3: 45348 | D3: =IF(TRIM(C3&"")="","",IFERROR(IF(INT(B3)=IF(ISNUMBER(C3),INT(C3),DATEVALUE(TRIM(C3))),"Correct","Incorrect"),"Incorrect")) -> Correct
A4: https://www.healthline.com/health/pregnancy/how-old-is-too-old-to-have-a-baby | B4: 44043 | C4: 44043 | D4: =IF(TRIM(C4&"")="","",IFERROR(IF(INT(B4)=IF(ISNUMBER(C4),INT(C4),DATEVALUE(TRIM(C4))),"Correct","Incorrect"),"Incorrect")) -> Correct
A5: https://www.healthline.com/nutrition/bananas-diabetes | B5: 45435 | C5: 45435 | D5: =IF(TRIM(C5&"")="","",IFERROR(IF(INT(B5)=IF(ISNUMBER(C5),INT(C5),DATEVALUE(TRIM(C5))),"Correct","Incorrect"),"Incorrect")) -> Correct
A6: https://www.healthline.com/health/diabetes/diabetic-friendly-grocery-list | B6: 45379 | C6: 45379 | D6: =IF(TRIM(C6&"")="","",IFERROR(IF(INT(B6)=IF(ISNUMBER(C6),INT(C6),DATEVALUE(TRIM(C6))),"Correct","Incorrect"),"Incorrect")) -> Correct
A7: https://www.healthline.com/health/nutrition/diabetes-nutrition-expert-how-to-build-a-blood-sugar-friendly-plate?utm_source=ReadNext | B7: 45993 | C7: 45993 | D7: =IF(TRIM(C7&"")="","",IFERROR(IF(INT(B7)=IF(ISNUMBER(C7),INT(C7),DATEVALUE(TRIM(C7))),"Correct","Incorrect"),"Incorrect")) -> Correct
A8: https://www.healthline.com/health/medicare/can-you-get-medicare-at-age-62 | B8: 45936 | C8: 45936 | D8: =IF(TRIM(C8&"")="","",IFERROR(IF(INT(B8)=IF(ISNUMBER(C8),INT(C8),DATEVALUE(TRIM(C8))),"Correct","Incorrect"),"Incorrect")) -> Correct
A9: https://www.healthline.com/health-news/eli-lilly-cuts-zepbound-prices | B9: 45532 | C9: 45532 | D9: =IF(TRIM(C9&"")="","",IFERROR(IF(INT(B9)=IF(ISNUMBER(C9),INT(C9),DATEVALUE(TRIM(C9))),"Correct","Incorrect"),"Incorrect")) -> Correct
A10: https://www.healthline.com/health/atopic-dermatitis/treatment-options | B10: 45842 | C10: 45842 | D10: =IF(TRIM(C10&"")="","",IFERROR(IF(INT(B10)=IF(ISNUMBER(C10),INT(C10),DATEVALUE(TRIM(C10))),"Correct","Incorrect"),"Incorrect")) -> Correct
A11: https://www.healthline.com/health/what-is-a-controlled-substance | B11: 45261 | C11: 45261 | D11: =IF(TRIM(C11&"")="","",IFERROR(IF(INT(B11)=IF(ISNUMBER(C11),INT(C11),DATEVALUE(TRIM(C11))),"Correct","Incorrect"),"Incorrect")) -> Correct
A12: https://www.healthline.com/health/heart-health/poor-balance-and-heart-health?utm_source=ReadNext | B12: 45988 | C12: 45988 | D12: =IF(TRIM(C12&"")="","",IFERROR(IF(INT(B12)=IF(ISNUMBER(C12),INT(C12),DATEVALUE(TRIM(C12))),"Correct","Incorrect"),"Incorrect")) -> Correct
A13: https://www.healthline.com/health/parenting/how-to-find-balance-as-a-new-mom | B13: 43738 | C13: 43738 | D13: =IF(TRIM(C13&"")="","",IFERROR(IF(INT(B13)=IF(ISNUMBER(C13),INT(C13),DATEVALUE(TRIM(C13))),"Correct","Incorrect"),"Incorrect")) -> Correct
... A101: https://www.healthline.com/nutrition/11-proven-benefits-of-ginger | B101: 45776 | C101: 45776 | D101: =IF(TRIM(C101&"")="","",IFERROR(IF(INT(B101)=IF(ISNUMBER(C101),INT(C101),DATEVALUE(TRIM(C101))),"Correct","Incorrect"),"Incorrect")) -> Correct
C102: Label accuracy (reviewed) | D102: =IFERROR(COUNTIF(D2:D101,"Correct")/(COUNTIF(D2:D101,"Correct")+COUNTIF(D2:D101,"Incorrect")),"") -> 1
C103: Reviewed / sampled | D103: =(COUNTIF(D2:D101,"Correct")+COUNTIF(D2:D101,"Incorrect"))&" / 100" -> 100 / 100

Sheet hollywood
A1: url | B1: automatic_timestamp | C1: manual_timestamp | D1: label_correctness
A2: https://www.hollywoodreporter.com/news/general-news/ron-howard-to-direct-lang-lang-biopic-4064874/ | B2: 44096 | C2: 44096 | D2: =IF(TRIM(C2&"")="","",IFERROR(IF(INT(B2)=IF(ISNUMBER(C2),INT(C2),DATEVALUE(TRIM(C2))),"Correct","Incorrect"),"Incorrect")) -> Correct
A3: https://www.hollywoodreporter.com/news/general-news/china-extends-holiday-contain-coronavirus-as-death-toll-rises-1273552/ | B3: 43856 | C3: 43856 | D3: =IF(TRIM(C3&"")="","",IFERROR(IF(INT(B3)=IF(ISNUMBER(C3),INT(C3),DATEVALUE(TRIM(C3))),"Correct","Incorrect"),"Incorrect")) -> Correct
A4: https://www.hollywoodreporter.com/news/general-news/kiefer-sutherland-why-he-joined-quibis-fugitive-i-fell-love-it-1306114/ | B4: 44048 | C4: 44048 | D4: =IF(TRIM(C4&"")="","",IFERROR(IF(INT(B4)=IF(ISNUMBER(C4),INT(C4),DATEVALUE(TRIM(C4))),"Correct","Incorrect"),"Incorrect")) -> Correct
A5: https://www.hollywoodreporter.com/news/general-news/gayle-king-katy-perry-flying-space-jeff-bezos-rocket-blue-origin-1236148874/ | B5: 45715 | C5: 45715 | D5: =IF(TRIM(C5&"")="","",IFERROR(IF(INT(B5)=IF(ISNUMBER(C5),INT(C5),DATEVALUE(TRIM(C5))),"Correct","Incorrect"),"Incorrect")) -> Correct
A6: https://www.hollywoodreporter.com/news/general-news/michel-filzi-to-succeed-paul-zilk-as-reed-midem-ceo-4066500/ | B6: 44098 | C6: 44098 | D6: =IF(TRIM(C6&"")="","",IFERROR(IF(INT(B6)=IF(ISNUMBER(C6),INT(C6),DATEVALUE(TRIM(C6))),"Correct","Incorrect"),"Incorrect")) -> Correct
A7: https://www.hollywoodreporter.com/news/general-news/batman-fan-film-with-surprising-cameos-goes-viral-4149140/ | B7: 44268 | C7: 44268 | D7: =IF(TRIM(C7&"")="","",IFERROR(IF(INT(B7)=IF(ISNUMBER(C7),INT(C7),DATEVALUE(TRIM(C7))),"Correct","Incorrect"),"Incorrect")) -> Correct
A8: https://www.hollywoodreporter.com/news/general-news/critics-notebook-chris-rock-kicks-off-comedy-tour-1235122859/ | B8: 44651 | C8: 44651 | D8: =IF(TRIM(C8&"")="","",IFERROR(IF(INT(B8)=IF(ISNUMBER(C8),INT(C8),DATEVALUE(TRIM(C8))),"Correct","Incorrect"),"Incorrect")) -> Correct
A9: https://www.hollywoodreporter.com/news/general-news/fox-news-christmas-tree-fire-arson-1235059136/ | B9: 44538 | C9: 44538 | D9: =IF(TRIM(C9&"")="","",IFERROR(IF(INT(B9)=IF(ISNUMBER(C9),INT(C9),DATEVALUE(TRIM(C9))),"Correct","Incorrect"),"Incorrect")) -> Correct
A10: https://www.hollywoodreporter.com/news/general-news/brett-ratner-immigrates-israel-1235608258/ | B10: 45202 | C10: 45202 | D10: =IF(TRIM(C10&"")="","",IFERROR(IF(INT(B10)=IF(ISNUMBER(C10),INT(C10),DATEVALUE(TRIM(C10))),"Correct","Incorrect"),"Incorrect")) -> Correct
A11: https://www.hollywoodreporter.com/news/general-news/elegance-bratton-trans-youth-focused-doc-pier-kids-i-hope-people-are-listening-1298109/ | B11: 43994 | C11: 43994 | D11: =IF(TRIM(C11&"")="","",IFERROR(IF(INT(B11)=IF(ISNUMBER(C11),INT(C11),DATEVALUE(TRIM(C11))),"Correct","Incorrect"),"Incorrect")) -> Correct
A12: https://www.hollywoodreporter.com/news/general-news/molly-shannon-women-hollywood-change-1235059337/ | B12: 44538 | C12: 44538 | D12: =IF(TRIM(C12&"")="","",IFERROR(IF(INT(B12)=IF(ISNUMBER(C12),INT(C12),DATEVALUE(TRIM(C12))),"Correct","Incorrect"),"Incorrect")) -> Correct
A13: https://www.hollywoodreporter.com/news/general-news/billie-eilish-becomes-youngest-record-year-winner-ever-at-grammys-2020-1273508/ | B13: 43856 | C13: 43856 | D13: =IF(TRIM(C13&"")="","",IFERROR(IF(INT(B13)=IF(ISNUMBER(C13),INT(C13),DATEVALUE(TRIM(C13))),"Correct","Incorrect"),"Incorrect")) -> Correct
... A101: https://www.hollywoodreporter.com/news/general-news/scarlett-johansson-versus-ai-voice-1235905245/ | B101: 45434 | C101: 45434 | D101: =IF(TRIM(C101&"")="","",IFERROR(IF(INT(B101)=IF(ISNUMBER(C101),INT(C101),DATEVALUE(TRIM(C101))),"Correct","Incorrect"),"Incorrect")) -> Correct
C102: Label accuracy (reviewed) | D102: =IFERROR(COUNTIF(D2:D101,"Correct")/(COUNTIF(D2:D101,"Correct")+COUNTIF(D2:D101,"Incorrect")),"") -> 1
C103: Reviewed / sampled | D103: =(COUNTIF(D2:D101,"Correct")+COUNTIF(D2:D101,"Incorrect"))&" / 100" -> 100 / 100

Sheet so
A1: url | B1: automatic_timestamp | C1: manual_timestamp | D1: label_correctness
A2: https://stackoverflow.com/questions/13749626/how-to-measure-the-stack-size-of-a-process?rq=3 | B2: 44755 | C2: 44755 | D2: =IF(TRIM(C2&"")="","",IFERROR(IF(INT(B2)=IF(ISNUMBER(C2),INT(C2),DATEVALUE(TRIM(C2))),"Correct","Incorrect"),"Incorrect")) -> Correct
A3: https://stackoverflow.com/questions/5074342/indexing-a-database?rq=3 | B3: 40596 | C3: 40596 | D3: =IF(TRIM(C3&"")="","",IFERROR(IF(INT(B3)=IF(ISNUMBER(C3),INT(C3),DATEVALUE(TRIM(C3))),"Correct","Incorrect"),"Incorrect")) -> Correct
A4: https://stackoverflow.com/questions/79737551 | B4: 45886 | C4: 45886 | D4: =IF(TRIM(C4&"")="","",IFERROR(IF(INT(B4)=IF(ISNUMBER(C4),INT(C4),DATEVALUE(TRIM(C4))),"Correct","Incorrect"),"Incorrect")) -> Correct
A5: https://stackoverflow.com/questions/7560736/c-sharp-and-flash-integration | B5: 42878 | C5: 42878 | D5: =IF(TRIM(C5&"")="","",IFERROR(IF(INT(B5)=IF(ISNUMBER(C5),INT(C5),DATEVALUE(TRIM(C5))),"Correct","Incorrect"),"Incorrect")) -> Correct
A6: https://stackoverflow.com/questions/881473/why-catch-and-rethrow-an-exception-in-c | B6: 45161 | C6: 45161 | D6: =IF(TRIM(C6&"")="","",IFERROR(IF(INT(B6)=IF(ISNUMBER(C6),INT(C6),DATEVALUE(TRIM(C6))),"Correct","Incorrect"),"Incorrect")) -> Correct
A7: https://stackoverflow.com/questions/1240005/how-to-embed-flash-in-desktop-application-in-net | B7: 40031 | C7: 40031 | D7: =IF(TRIM(C7&"")="","",IFERROR(IF(INT(B7)=IF(ISNUMBER(C7),INT(C7),DATEVALUE(TRIM(C7))),"Correct","Incorrect"),"Incorrect")) -> Correct
A8: https://stackoverflow.com/questions/27922288/complicated-linq-to-sql-query | B8: 42017 | C8: 42017 | D8: =IF(TRIM(C8&"")="","",IFERROR(IF(INT(B8)=IF(ISNUMBER(C8),INT(C8),DATEVALUE(TRIM(C8))),"Correct","Incorrect"),"Incorrect")) -> Correct
A9: https://stackoverflow.com/questions/2236113/shell-file-size-in-linux?rq=3 | B9: 44581 | C9: 44581 | D9: =IF(TRIM(C9&"")="","",IFERROR(IF(INT(B9)=IF(ISNUMBER(C9),INT(C9),DATEVALUE(TRIM(C9))),"Correct","Incorrect"),"Incorrect")) -> Correct
A10: https://stackoverflow.com/questions/719983/calculating-the-probability-of-a-token-being-spam-in-a-bayesian-spam-filter | B10: 39934 | C10: 39934 | D10: =IF(TRIM(C10&"")="","",IFERROR(IF(INT(B10)=IF(ISNUMBER(C10),INT(C10),DATEVALUE(TRIM(C10))),"Correct","Incorrect"),"Incorrect")) -> Correct
A11: https://stackoverflow.com/questions/31494188/what-does-the-code-mean-in-c | B11: 42203 | C11: 42203 | D11: =IF(TRIM(C11&"")="","",IFERROR(IF(INT(B11)=IF(ISNUMBER(C11),INT(C11),DATEVALUE(TRIM(C11))),"Correct","Incorrect"),"Incorrect")) -> Correct
A12: https://stackoverflow.com/questions/22048213/cant-catch-an-exception | B12: 41708 | C12: 41708 | D12: =IF(TRIM(C12&"")="","",IFERROR(IF(INT(B12)=IF(ISNUMBER(C12),INT(C12),DATEVALUE(TRIM(C12))),"Correct","Incorrect"),"Incorrect")) -> Correct
A13: https://stackoverflow.com/questions/9704602/php-variables-by-ref-or-by-value | B13: 42878 | C13: 42878 | D13: =IF(TRIM(C13&"")="","",IFERROR(IF(INT(B13)=IF(ISNUMBER(C13),INT(C13),DATEVALUE(TRIM(C13))),"Correct","Incorrect"),"Incorrect")) -> Correct
... A101: https://stackoverflow.com/questions/2731405/how-can-you-determine-what-font-from-the-css-stack-is-being-used | B101: 42878 | C101: 42878 | D101: =IF(TRIM(C101&"")="","",IFERROR(IF(INT(B101)=IF(ISNUMBER(C101),INT(C101),DATEVALUE(TRIM(C101))),"Correct","Incorrect"),"Incorrect")) -> Correct
C102: Label accuracy (reviewed) | D102: =IFERROR(COUNTIF(D2:D101,"Correct")/(COUNTIF(D2:D101,"Correct")+COUNTIF(D2:D101,"Incorrect")),"") -> 1
C103: Reviewed / sampled | D103: =(COUNTIF(D2:D101,"Correct")+COUNTIF(D2:D101,"Incorrect"))&" / 100" -> 100 / 100

Sheet toh
A1: url | B1: automatic_timestamp | C1: manual_timestamp | D1: label_correctness
A2: https://www.tasteofhome.com/recipes/watermelon-and-key-lime-cream-cheese-dip/ | B2: 45715 | C2: 45715 | D2: =IF(TRIM(C2&"")="","",IFERROR(IF(INT(B2)=IF(ISNUMBER(C2),INT(C2),DATEVALUE(TRIM(C2))),"Correct","Incorrect"),"Incorrect")) -> Correct
A3: https://www.tasteofhome.com/recipes/gingerbread-ice-cream/ | B3: 45750 | C3: 45750 | D3: =IF(TRIM(C3&"")="","",IFERROR(IF(INT(B3)=IF(ISNUMBER(C3),INT(C3),DATEVALUE(TRIM(C3))),"Correct","Incorrect"),"Incorrect")) -> Correct
A4: https://www.tasteofhome.com/recipes/lemon-supreme-pie/ | B4: 45564 | C4: 45564 | D4: =IF(TRIM(C4&"")="","",IFERROR(IF(INT(B4)=IF(ISNUMBER(C4),INT(C4),DATEVALUE(TRIM(C4))),"Correct","Incorrect"),"Incorrect")) -> Correct
A5: https://www.tasteofhome.com/recipes/blueberry-sour-cream-coffee-cake/ | B5: 45518 | C5: 45518 | D5: =IF(TRIM(C5&"")="","",IFERROR(IF(INT(B5)=IF(ISNUMBER(C5),INT(C5),DATEVALUE(TRIM(C5))),"Correct","Incorrect"),"Incorrect")) -> Correct
A6: https://www.tasteofhome.com/recipes/tam-to-one-pot-tomato-salmon/ | B6: 45916 | C6: 45916 | D6: =IF(TRIM(C6&"")="","",IFERROR(IF(INT(B6)=IF(ISNUMBER(C6),INT(C6),DATEVALUE(TRIM(C6))),"Correct","Incorrect"),"Incorrect")) -> Correct
A7: https://www.tasteofhome.com/recipes/cheeseburger-casserole-2/ | B7: 45677 | C7: 45677 | D7: =IF(TRIM(C7&"")="","",IFERROR(IF(INT(B7)=IF(ISNUMBER(C7),INT(C7),DATEVALUE(TRIM(C7))),"Correct","Incorrect"),"Incorrect")) -> Correct
A8: https://www.tasteofhome.com/recipes/banana-oat-breakfast-cookies/ | B8: 45557 | C8: 45557 | D8: =IF(TRIM(C8&"")="","",IFERROR(IF(INT(B8)=IF(ISNUMBER(C8),INT(C8),DATEVALUE(TRIM(C8))),"Correct","Incorrect"),"Incorrect")) -> Correct
A9: https://www.tasteofhome.com/recipes/strawberry-pretzel-salad-dip/ | B9: 45777 | C9: 45777 | D9: =IF(TRIM(C9&"")="","",IFERROR(IF(INT(B9)=IF(ISNUMBER(C9),INT(C9),DATEVALUE(TRIM(C9))),"Correct","Incorrect"),"Incorrect")) -> Correct
A10: https://www.tasteofhome.com/recipes/pumpkin-cake-with-whipped-cinnamon-frosting/ | B10: 45425 | C10: 45425 | D10: =IF(TRIM(C10&"")="","",IFERROR(IF(INT(B10)=IF(ISNUMBER(C10),INT(C10),DATEVALUE(TRIM(C10))),"Correct","Incorrect"),"Incorrect")) -> Correct
A11: https://www.tasteofhome.com/recipes/homemade-pumpkin-pasta/ | B11: 45883 | C11: 45883 | D11: =IF(TRIM(C11&"")="","",IFERROR(IF(INT(B11)=IF(ISNUMBER(C11),INT(C11),DATEVALUE(TRIM(C11))),"Correct","Incorrect"),"Incorrect")) -> Correct
A12: https://www.tasteofhome.com/recipes/crab-cake-stuffed-mushrooms/ | B12: 45593 | C12: 45593 | D12: =IF(TRIM(C12&"")="","",IFERROR(IF(INT(B12)=IF(ISNUMBER(C12),INT(C12),DATEVALUE(TRIM(C12))),"Correct","Incorrect"),"Incorrect")) -> Correct
A13: https://www.tasteofhome.com/recipes/scalloped-sweet-potatoes/ | B13: 45574 | C13: 45574 | D13: =IF(TRIM(C13&"")="","",IFERROR(IF(INT(B13)=IF(ISNUMBER(C13),INT(C13),DATEVALUE(TRIM(C13))),"Correct","Incorrect"),"Incorrect")) -> Correct
... A101: https://www.tasteofhome.com/recipes/smoked-beef-short-ribs/ | B101: 45558 | C101: 45558 | D101: =IF(TRIM(C101&"")="","",IFERROR(IF(INT(B101)=IF(ISNUMBER(C101),INT(C101),DATEVALUE(TRIM(C101))),"Correct","Incorrect"),"Incorrect")) -> Correct
C102: Label accuracy (reviewed) | D102: =IFERROR(COUNTIF(D2:D101,"Correct")/(COUNTIF(D2:D101,"Correct")+COUNTIF(D2:D101,"Incorrect")),"") -> 1
C103: Reviewed / sampled | D103: =(COUNTIF(D2:D101,"Correct")+COUNTIF(D2:D101,"Incorrect"))&" / 100" -> 100 / 100

Sheet treasury
A1: url | B1: automatic_timestamp | C1: manual_timestamp | D1: label_correctness
A2: https://home.treasury.gov/news/press-releases/sm672 | B2: 43584 | C2: 43584 | D2: =IF(TRIM(C2&"")="","",IFERROR(IF(INT(B2)=IF(ISNUMBER(C2),INT(C2),DATEVALUE(TRIM(C2))),"Correct","Incorrect"),"Incorrect")) -> Correct
A3: https://home.treasury.gov/news/press-releases/jy1962 | B3: 45267 | C3: 45267 | D3: =IF(TRIM(C3&"")="","",IFERROR(IF(INT(B3)=IF(ISNUMBER(C3),INT(C3),DATEVALUE(TRIM(C3))),"Correct","Incorrect"),"Incorrect")) -> Correct
A4: https://home.treasury.gov/news/press-releases/jy0916 | B4: 44781 | C4: 44781 | D4: =IF(TRIM(C4&"")="","",IFERROR(IF(INT(B4)=IF(ISNUMBER(C4),INT(C4),DATEVALUE(TRIM(C4))),"Correct","Incorrect"),"Incorrect")) -> Correct
A5: https://home.treasury.gov/news/press-releases/jl0205 | B5: 42286 | C5: 42286 | D5: =IF(TRIM(C5&"")="","",IFERROR(IF(INT(B5)=IF(ISNUMBER(C5),INT(C5),DATEVALUE(TRIM(C5))),"Correct","Incorrect"),"Incorrect")) -> Correct
A6: https://home.treasury.gov/news/press-releases/sm0338 | B6: 43196 | C6: 43196 | D6: =IF(TRIM(C6&"")="","",IFERROR(IF(INT(B6)=IF(ISNUMBER(C6),INT(C6),DATEVALUE(TRIM(C6))),"Correct","Incorrect"),"Incorrect")) -> Correct
A7: https://home.treasury.gov/news/press-releases/jl0342 | B7: 42405 | C7: 42405 | D7: =IF(TRIM(C7&"")="","",IFERROR(IF(INT(B7)=IF(ISNUMBER(C7),INT(C7),DATEVALUE(TRIM(C7))),"Correct","Incorrect"),"Incorrect")) -> Correct
A8: https://home.treasury.gov/news/press-releases/sm624 | B8: 43536 | C8: 43536 | D8: =IF(TRIM(C8&"")="","",IFERROR(IF(INT(B8)=IF(ISNUMBER(C8),INT(C8),DATEVALUE(TRIM(C8))),"Correct","Incorrect"),"Incorrect")) -> Correct
A9: https://home.treasury.gov/news/press-releases/jl0178 | B9: 42271 | C9: 42271 | D9: =IF(TRIM(C9&"")="","",IFERROR(IF(INT(B9)=IF(ISNUMBER(C9),INT(C9),DATEVALUE(TRIM(C9))),"Correct","Incorrect"),"Incorrect")) -> Correct
A10: https://home.treasury.gov/news/press-releases/sm448 | B10: 43312 | C10: 43312 | D10: =IF(TRIM(C10&"")="","",IFERROR(IF(INT(B10)=IF(ISNUMBER(C10),INT(C10),DATEVALUE(TRIM(C10))),"Correct","Incorrect"),"Incorrect")) -> Correct
A11: https://home.treasury.gov/news/press-releases/sm996 | B11: 43955 | C11: 43955 | D11: =IF(TRIM(C11&"")="","",IFERROR(IF(INT(B11)=IF(ISNUMBER(C11),INT(C11),DATEVALUE(TRIM(C11))),"Correct","Incorrect"),"Incorrect")) -> Correct
A12: https://home.treasury.gov/news/press-releases/jy1188 | B12: 44939 | C12: 44939 | D12: =IF(TRIM(C12&"")="","",IFERROR(IF(INT(B12)=IF(ISNUMBER(C12),INT(C12),DATEVALUE(TRIM(C12))),"Correct","Incorrect"),"Incorrect")) -> Correct
A13: https://home.treasury.gov/news/press-releases/jy0120 | B13: 44299 | C13: 44299 | D13: =IF(TRIM(C13&"")="","",IFERROR(IF(INT(B13)=IF(ISNUMBER(C13),INT(C13),DATEVALUE(TRIM(C13))),"Correct","Incorrect"),"Incorrect")) -> Correct
... A101: https://home.treasury.gov/news/press-releases/jy2425 | B101: 45464 | C101: 45463 | D101: =IF(TRIM(C101&"")="","",IFERROR(IF(INT(B101)=IF(ISNUMBER(C101),INT(C101),DATEVALUE(TRIM(C101))),"Correct","Incorrect"),"Incorrect")) -> Incorrect
C102: Label accuracy (reviewed) | D102: =IFERROR(COUNTIF(D2:D101,"Correct")/(COUNTIF(D2:D101,"Correct")+COUNTIF(D2:D101,"Incorrect")),"") -> 0.96
C103: Reviewed / sampled | D103: =(COUNTIF(D2:D101,"Correct")+COUNTIF(D2:D101,"Incorrect"))&" / 100" -> 100 / 100

Sheet voa
A1: url | B1: automatic_timestamp | C1: manual_timestamp | D1: label_correctness
A2: https://www.voanews.com/a/nasa-s-future-closely-connected-to-commercial-space-entrepreneurs-/7910390.html | B2: 45648 | C2: 45648 | D2: =IF(TRIM(C2&"")="","",IFERROR(IF(INT(B2)=IF(ISNUMBER(C2),INT(C2),DATEVALUE(TRIM(C2))),"Correct","Incorrect"),"Incorrect")) -> Correct
A3: https://www.voanews.com/a/voa-mandarin-china-retaliates-against-new-us-tariffs/7997738.html | B3: 45720 | C3: 45720 | D3: =IF(TRIM(C3&"")="","",IFERROR(IF(INT(B3)=IF(ISNUMBER(C3),INT(C3),DATEVALUE(TRIM(C3))),"Correct","Incorrect"),"Incorrect")) -> Correct
A4: https://www.voanews.com/a/indonesia-expands-qr-payment-system-to-increase-chinese-spending-/7539240.html | B4: 45374 | C4: 45374 | D4: =IF(TRIM(C4&"")="","",IFERROR(IF(INT(B4)=IF(ISNUMBER(C4),INT(C4),DATEVALUE(TRIM(C4))),"Correct","Incorrect"),"Incorrect")) -> Correct
A5: https://www.voanews.com/a/us-national-guard-soldier-shoots-injures-migrant-in-texas/6927920.html | B5: 44946 | C5: 44946 | D5: =IF(TRIM(C5&"")="","",IFERROR(IF(INT(B5)=IF(ISNUMBER(C5),INT(C5),DATEVALUE(TRIM(C5))),"Correct","Incorrect"),"Incorrect")) -> Correct
A6: https://www.voanews.com/a/why-almost-all-muslim-american-charitable-donations-remain-in-us/7536008.html | B6: 45371 | C6: 45371 | D6: =IF(TRIM(C6&"")="","",IFERROR(IF(INT(B6)=IF(ISNUMBER(C6),INT(C6),DATEVALUE(TRIM(C6))),"Correct","Incorrect"),"Incorrect")) -> Correct
A7: https://www.voanews.com/a/french-citizen-held-in-iran-sentenced-to-five-years-in-prison/7346817.html | B7: 45238 | C7: 45238 | D7: =IF(TRIM(C7&"")="","",IFERROR(IF(INT(B7)=IF(ISNUMBER(C7),INT(C7),DATEVALUE(TRIM(C7))),"Correct","Incorrect"),"Incorrect")) -> Correct
A8: https://www.voanews.com/a/colorado-ukrainian-community-offers-job-fair-for-new-arrivals-/7247962.html | B8: 45168 | C8: 45168 | D8: =IF(TRIM(C8&"")="","",IFERROR(IF(INT(B8)=IF(ISNUMBER(C8),INT(C8),DATEVALUE(TRIM(C8))),"Correct","Incorrect"),"Incorrect")) -> Correct
A9: https://www.voanews.com/a/in-the-philippines-some-progress-for-media-rights-but-risks-remain/7879874.html | B9: 45624 | C9: 45624 | D9: =IF(TRIM(C9&"")="","",IFERROR(IF(INT(B9)=IF(ISNUMBER(C9),INT(C9),DATEVALUE(TRIM(C9))),"Correct","Incorrect"),"Incorrect")) -> Correct
A10: https://www.voanews.com/a/how-belarusian-fighters-in-ukraine-evolved-into-prominent-force-against-russian-invasion/6512220.html | B10: 44653 | C10: 44653 | D10: =IF(TRIM(C10&"")="","",IFERROR(IF(INT(B10)=IF(ISNUMBER(C10),INT(C10),DATEVALUE(TRIM(C10))),"Correct","Incorrect"),"Incorrect")) -> Correct
A11: https://www.voanews.com/a/russia-pounds-kharkiv-donetsk-regions/7767074.html | B11: 45535 | C11: 45535 | D11: =IF(TRIM(C11&"")="","",IFERROR(IF(INT(B11)=IF(ISNUMBER(C11),INT(C11),DATEVALUE(TRIM(C11))),"Correct","Incorrect"),"Incorrect")) -> Correct
A12: https://www.voanews.com/a/fact-check-china-hack-microsoft-exchange/6743059.html | B12: 44398 | C12: 44398 | D12: =IF(TRIM(C12&"")="","",IFERROR(IF(INT(B12)=IF(ISNUMBER(C12),INT(C12),DATEVALUE(TRIM(C12))),"Correct","Incorrect"),"Incorrect")) -> Correct
A13: https://www.voanews.com/a/envoy-absence-of-sudan-army-delegation-hobbles-progress-in-us-mediated-peace-talks-/7748745.html | B13: 45523 | C13: 45523 | D13: =IF(TRIM(C13&"")="","",IFERROR(IF(INT(B13)=IF(ISNUMBER(C13),INT(C13),DATEVALUE(TRIM(C13))),"Correct","Incorrect"),"Incorrect")) -> Correct
... A101: https://www.voanews.com/a/azerbaijan-issues-travel-ban-for-journalist-/6511641.html | B101: 44652 | C101: 44652 | D101: =IF(TRIM(C101&"")="","",IFERROR(IF(INT(B101)=IF(ISNUMBER(C101),INT(C101),DATEVALUE(TRIM(C101))),"Correct","Incorrect"),"Incorrect")) -> Correct
C102: Label accuracy (reviewed) | D102: =IFERROR(COUNTIF(D2:D101,"Correct")/(COUNTIF(D2:D101,"Correct")+COUNTIF(D2:D101,"Incorrect")),"") -> 0.98
C103: Reviewed / sampled | D103: =(COUNTIF(D2:D101,"Correct")+COUNTIF(D2:D101,"Incorrect"))&" / 100" -> 100 / 100

Sheet Summary
A1: domain | B1: label_accuracy
A2: apple | B2: =IF(apple!D102="","",apple!D102) -> 1
A3: au | B3: =IF(au!D102="","",au!D102) -> 1
A4: cafnr | B4: =IF(cafnr!D102="","",cafnr!D102) -> 1
A5: coas | B5: =IF(coas!D102="","",coas!D102) -> 1
A6: google | B6: =IF(google!D102="","",google!D102) -> 1
A7: healthline | B7: =IF(healthline!D102="","",healthline!D102) -> 1
A8: hollywood | B8: =IF(hollywood!D102="","",hollywood!D102) -> 1
A9: so | B9: =IF(so!D102="","",so!D102) -> 1
A10: toh | B10: =IF(toh!D102="","",toh!D102) -> 1
A11: treasury | B11: =IF(treasury!D102="","",treasury!D102) -> 0.96
A12: voa | B12: =IF(voa!D102="","",voa!D102) -> 0.98
